LICENSE.txt
MANIFEST.in
README.md
setup.cfg
setup.py
pdfaddyemei/__init__.py
pdfaddyemei/pdfaddyemei.pyd
pdfaddyemei/pdfaddyemeiResultUi.pyd
pdfaddyemei.egg-info/PKG-INFO
pdfaddyemei.egg-info/SOURCES.txt
pdfaddyemei.egg-info/dependency_links.txt
pdfaddyemei.egg-info/top_level.txt
pdfaddyemei/function/__init__.py
pdfaddyemei/function/pdfaddyemei.pyd
pdfaddyemei/package/__init__.py
pdfaddyemei/package/reportlab/__init__.py
pdfaddyemei/package/reportlab/rl_config.py
pdfaddyemei/package/reportlab/rl_settings.py
pdfaddyemei/package/reportlab/graphics/__init__.py
pdfaddyemei/package/reportlab/graphics/renderPDF.py
pdfaddyemei/package/reportlab/graphics/renderPM.py
pdfaddyemei/package/reportlab/graphics/renderPS.py
pdfaddyemei/package/reportlab/graphics/renderSVG.py
pdfaddyemei/package/reportlab/graphics/renderbase.py
pdfaddyemei/package/reportlab/graphics/shapes.py
pdfaddyemei/package/reportlab/graphics/svgpath.py
pdfaddyemei/package/reportlab/graphics/testdrawings.py
pdfaddyemei/package/reportlab/graphics/testshapes.py
pdfaddyemei/package/reportlab/graphics/transform.py
pdfaddyemei/package/reportlab/graphics/utils.py
pdfaddyemei/package/reportlab/graphics/widgetbase.py
pdfaddyemei/package/reportlab/graphics/barcode/__init__.py
pdfaddyemei/package/reportlab/graphics/barcode/code128.py
pdfaddyemei/package/reportlab/graphics/barcode/code39.py
pdfaddyemei/package/reportlab/graphics/barcode/code93.py
pdfaddyemei/package/reportlab/graphics/barcode/common.py
pdfaddyemei/package/reportlab/graphics/barcode/dmtx.py
pdfaddyemei/package/reportlab/graphics/barcode/eanbc.py
pdfaddyemei/package/reportlab/graphics/barcode/ecc200datamatrix.py
pdfaddyemei/package/reportlab/graphics/barcode/fourstate.py
pdfaddyemei/package/reportlab/graphics/barcode/lto.py
pdfaddyemei/package/reportlab/graphics/barcode/qr.py
pdfaddyemei/package/reportlab/graphics/barcode/qrencoder.py
pdfaddyemei/package/reportlab/graphics/barcode/test.py
pdfaddyemei/package/reportlab/graphics/barcode/usps.py
pdfaddyemei/package/reportlab/graphics/barcode/usps4s.py
pdfaddyemei/package/reportlab/graphics/barcode/widgets.py
